MANIFEST.in
README.md
setup.py
libmahjong/__init__.py
libmahjong/libmahjong.pyd
libmahjong/libmahjong.so
riichiroyale/__init__.py
riichiroyale/__main__.py
riichiroyale.egg-info/PKG-INFO
riichiroyale.egg-info/SOURCES.txt
riichiroyale.egg-info/dependency_links.txt
riichiroyale.egg-info/entry_points.txt
riichiroyale.egg-info/requires.txt
riichiroyale.egg-info/top_level.txt
riichiroyale/audio/__init__.py
riichiroyale/audio/soundmanager.py
riichiroyale/game/__init__.py
riichiroyale/game/board.py
riichiroyale/game/boardmanager.py
riichiroyale/game/call.py
riichiroyale/game/dialogmanager.py
riichiroyale/game/gameevent.py
riichiroyale/game/loadStory.py
riichiroyale/game/match.py
riichiroyale/game/meld.py
riichiroyale/game/player.py
riichiroyale/game/playermanager.py
riichiroyale/game/storagemanager.py
riichiroyale/game/stubbornbot.py
riichiroyale/game/tutorialbot.py
riichiroyale/game/wall.py
riichiroyale/resources/__init__.py
riichiroyale/resources/theme.json
riichiroyale/resources/audio/music/attribution.txt
riichiroyale/resources/audio/music/game1.ogg
riichiroyale/resources/audio/music/game2.ogg
riichiroyale/resources/audio/music/game3.ogg
riichiroyale/resources/audio/music/lobby.ogg
riichiroyale/resources/audio/tileclack/clack-01.ogg
riichiroyale/resources/audio/tileclack/clack-02.ogg
riichiroyale/resources/audio/tileclack/clack-03.ogg
riichiroyale/resources/audio/tileclack/clack-04.ogg
riichiroyale/resources/audio/tileclack/clack-05.ogg
riichiroyale/resources/audio/tileclack/clack-06.ogg
riichiroyale/resources/audio/tileclack/clack-07.ogg
riichiroyale/resources/audio/tileclack/clack-08.ogg
riichiroyale/resources/audio/tileclack/clack-09.ogg
riichiroyale/resources/audio/tileclack/clack-10.ogg
riichiroyale/resources/audio/tileclack/clack-11.ogg
riichiroyale/resources/audio/tileclack/clack-12.ogg
riichiroyale/resources/audio/tileclack/clack-13.ogg
riichiroyale/resources/audio/tileclack/clack-14.ogg
riichiroyale/resources/audio/tileclack/clack-15.ogg
riichiroyale/resources/audio/tileclack/clack-16.ogg
riichiroyale/resources/audio/tileclack/clack-17.ogg
riichiroyale/resources/fonts/SourceSans3-Black.ttf
riichiroyale/resources/fonts/SourceSans3-BlackIt.ttf
