Metadata-Version: 2.1
Name: riichiroyale
Version: 1.0.3
Summary: Singleplayer Riichi Mahjong Game
Home-page: https://github.com/HartleyAHartley/RiichiRoyale
Author: Christopher Miller
Author-email: cmiller548@gmail.com
License: UNKNOWN
Platform: UNKNOWN
Classifier: Programming Language :: Python :: 3
Classifier: Operating System :: Microsoft :: Windows
Classifier: Operating System :: Unix
Requires-Python: >=3.6
